cognee_community_hybrid_adapter_falkor/FalkorDatasetDatabaseHandlerGraphLocal.py
cognee_community_hybrid_adapter_falkor/FalkorDatasetDatabaseHandlerVectorLocal.py
cognee_community_hybrid_adapter_falkor/__init__.py
cognee_community_hybrid_adapter_falkor/falkor_adapter.py
cognee_community_hybrid_adapter_falkor/register.py
cognee_community_hybrid_adapter_falkor-0.2.0.dist-info/METADATA
cognee_community_hybrid_adapter_falkor-0.2.0.dist-info/WHEEL
cognee_community_hybrid_adapter_falkor-0.2.0.dist-info/RECORD
