Metadata-Version: 2.4
Name: cognee-community-hybrid-adapter-falkor
Version: 0.2.0
Summary: Falkor hybrid database adapter for cognee
Requires-Python: >=3.11,<=3.13
Classifier: Programming Language :: Python :: 3
Classifier: Programming Language :: Python :: 3.11
Classifier: Programming Language :: Python :: 3.12
Classifier: Programming Language :: Python :: 3.13
Provides-Extra: dev
Requires-Dist: cognee (==0.5.1)
Requires-Dist: falkordb (>=1.0.9,<2.0.0)
Requires-Dist: instructor (>=1.11)
Requires-Dist: mypy (>=1.0.0) ; extra == "dev"
Requires-Dist: starlette (>=0.48.0)
Requires-Dist: types-requests ; extra == "dev"
